ChatTTS/__init__.py
ChatTTS/__main__.py
ChatTTS/cli.py
ChatTTS/core.py
ChatTTS/experimental/__init__.py
ChatTTS/experimental/llm.py
ChatTTS/infer/__init__.py
ChatTTS/infer/api.py
ChatTTS/model/__init__.py
ChatTTS/model/dvae.py
ChatTTS/model/gpt.py
ChatTTS/utils/__init__.py
ChatTTS/utils/gpu_utils.py
ChatTTS/utils/infer_utils.py
ChatTTS/utils/io_utils.py
chattts_fork-0.0.8.dist-info/LICENSE
chattts_fork-0.0.8.dist-info/METADATA
chattts_fork-0.0.8.dist-info/WHEEL
chattts_fork-0.0.8.dist-info/entry_points.txt
chattts_fork-0.0.8.dist-info/top_level.txt
chattts_fork-0.0.8.dist-info/RECORD
