Metadata-Version: 2.1
Name: chattts-fork
Version: 0.0.8
Summary: fork from https://github.com/2noise/ChatTTS to PYPI
Home-page: https://github.com/yihong0618/ChatTTS
Author: lich99 CH.Li, yihong0618
Author-email: zouzou0208@gmail.com
License: # Attribution-NonCommercial-NoDerivatives 4.0 International
Classifier: Programming Language :: Python :: 3.9
Classifier: Programming Language :: Python :: 3.10
Classifier: Programming Language :: Python :: 3.11
Classifier: Programming Language :: Python :: 3.12
Classifier: Operating System :: OS Independent
Requires-Python: >=3.9
License-File: LICENSE
Requires-Dist: omegaconf ~=2.3.0
Requires-Dist: torch ~=2.0
Requires-Dist: tqdm
Requires-Dist: einops
Requires-Dist: vector-quantize-pytorch
Requires-Dist: transformers ~=4.41.1
Requires-Dist: vocos
